LICENSE.txt
MANIFEST.in
README
requirements.txt
setup.cfg
setup.py
bin/hcf
hurricane_factory/__init__.py
hurricane_factory/commands.py
hurricane_factory.egg-info/PKG-INFO
hurricane_factory.egg-info/SOURCES.txt
hurricane_factory.egg-info/dependency_links.txt
hurricane_factory.egg-info/requires.txt
hurricane_factory.egg-info/top_level.txt