Metadata-Version: 1.0
Name: hurricane-factory
Version: 0.1.5
Summary: Manage CloudFormation at Massive Scale
Home-page: https://github.com/trek10inc/hurricane-factory
Author: Jared Short
Author-email: jaredlshort@gmail.com
License: MIT
Keywords: aws,cloudformation,management,orchestration
Platform: UNKNOWN
